monotonic.py
monotonic-1.4.dist-info/DESCRIPTION.rst
monotonic-1.4.dist-info/METADATA
monotonic-1.4.dist-info/RECORD
monotonic-1.4.dist-info/WHEEL
monotonic-1.4.dist-info/metadata.json
monotonic-1.4.dist-info/top_level.txt
