Metadata-Version: 1.1
Name: monotonic
Version: 1.4
Summary: An implementation of time.monotonic() for Python 2 & < 3.3
Home-page: https://github.com/atdt/monotonic
Author: Ori Livneh
Author-email: ori@wikimedia.org
License: Apache
Platform: UNKNOWN
Classifier: Development Status :: 5 - Production/Stable
Classifier: License :: OSI Approved :: Apache Software License
Classifier: Programming Language :: Python :: 2
Classifier: Programming Language :: Python :: 3
Classifier: Topic :: Software Development :: Libraries :: Python Modules
